COPYRIGHT
LICENSE
MANIFEST.in
NOTICE
README.md
pyproject.toml
setup.cfg
setup.py
prometheus_flux.egg-info/PKG-INFO
prometheus_flux.egg-info/SOURCES.txt
prometheus_flux.egg-info/dependency_links.txt
prometheus_flux.egg-info/entry_points.txt
prometheus_flux.egg-info/not-zip-safe
prometheus_flux.egg-info/requires.txt
prometheus_flux.egg-info/top_level.txt
promflux/__init__.py
promflux/logger.py
promflux/metrics.py
promflux/registry.py
promflux/server.py
promflux/version.py
promflux/views.py