Metadata-Version: 2.1
Name: prometheus-flux
Version: 0.0.0
Summary: Export flux instance metrics to Prometheus
Home-page: https://github.com/converged-computing/prometheus-flux
Author: Vanessa Sochat
Author-email: vsoch@users.noreply.github.com
Maintainer: Vanessa Sochat
License: LICENSE
Keywords: cloud,flux,flux-framework,monitoring
Platform: UNKNOWN
Classifier: Intended Audience :: Science/Research
Classifier: Intended Audience :: Developers
Classifier: License :: OSI Approved :: MIT License
Classifier: Programming Language :: Python
Classifier: Topic :: Software Development
Classifier: Topic :: Scientific/Engineering
Classifier: Operating System :: Unix
Classifier: Programming Language :: Python :: 3.8
Provides-Extra: all
License-File: LICENSE
License-File: NOTICE
